swurl/__init__.py
swurl/wurl.py
swurl-0.1.0.dist-info/LICENSE
swurl-0.1.0.dist-info/WHEEL
swurl-0.1.0.dist-info/METADATA
swurl-0.1.0.dist-info/RECORD
