Metadata-Version: 2.1
Name: swurl
Version: 0.1.0
Summary: simple Pathlib-like usage of URLs
Author-email: Steve Berardi <hello@steveberardi.com>
Classifier: License :: OSI Approved :: MIT License
Project-URL: Home, https://github.com/steveberardi/wurl
